{"assets":[{"id":"8","layers":[{"ind":7,"ty":4,"parent":6,"ks":{},"ef":[{"ty":29,"ef":[{"ty":0,"nm":"","v":{"a":1,"k":[{"t":0,"s":[33.33],"h":1},{"t":11.562,"s":[33.33],"i":{"x":0.598,"y":0.032},"o":{"x":0.129,"y":0.002}},{"t":19.542,"s":[33.22],"i":{"x":0.737,"y":0.421},"o":{"x":0.437,"y":0.147}},{"t":27.522,"s":[32.43],"i":{"x":0.661,"y":0.66},"o":{"x":0.413,"y":0.41}},{"t":27.93,"s":[32.34],"i":{"x":0.601,"y":0.859},"o":{"x":0.378,"y":0.532}},{"t":36.162,"s":[31.01],"i":{"x":0.641,"y":0.629},"o":{"x":0.324,"y":0.372}},{"t":38.217,"s":[30.91],"i":{"x":0.737,"y":0.819},"o":{"x":0.451,"y":0.43}},{"t":40.272,"s":[30.79],"i":{"x":0.501,"y":0.477},"o":{"x":0.277,"y":0.281}},{"t":42.288,"s":[30.71],"i":{"x":0.727,"y":0.837},"o":{"x":0.343,"y":0.369}},{"t":44.304,"s":[30.63],"i":{"x":0.597,"y":0.996},"o":{"x":0.312,"y":0.249}},{"t":47.746551,"s":[30.46],"h":1},{"t":47.874,"s":[30.46],"i":{"x":0.753,"y":0.635},"o":{"x":0.372,"y":0.016}},{"t":49.193951,"s":[30.49],"i":{"x":0.627,"y":0.976},"o":{"x":0.306,"y":0.457}},{"t":50.513903,"s":[30.51],"h":1},{"t":50.566865,"s":[30.51],"i":{"x":0.54,"y":0.17},"o":{"x":0.245,"y":0.017}},{"t":51.791433,"s":[30.48],"i":{"x":0.71,"y":0.802},"o":{"x":0.336,"y":0.334}},{"t":53.016,"s":[30.43],"i":{"x":0.627,"y":0.996},"o":{"x":0.347,"y":0.519}},{"t":54.645537,"s":[30.36],"h":1},{"t":54.663009,"s":[30.36],"i":{"x":0.487,"y":0.097},"o":{"x":0.177,"y":0.005}},{"t":55.746,"s":[30.39],"i":{"x":0.622,"y":0.978},"o":{"x":0.328,"y":0.415}},{"t":57.331344,"s":[30.44],"h":1},{"t":57.368438,"s":[30.44],"i":{"x":0.71,"y":0.536},"o":{"x":0.402,"y":0.022}},{"t":58.692355,"s":[30.39],"i":{"x":0.634,"y":0.987},"o":{"x":0.28,"y":0.395}},{"t":60.016272,"s":[30.34],"h":1},{"t":60.162,"s":[30.34],"i":{"x":1,"y":1},"o":{"x":0,"y":0}},{"t":62.736,"s":[30.35],"h":1},{"t":64.128055,"s":[30.35],"i":{"x":0.68,"y":0.654},"o":{"x":0.589,"y":0.513}},{"t":64.513466,"s":[30.34],"i":{"x":0.771,"y":0.757},"o":{"x":0.179,"y":0.16}},{"t":64.898876,"s":[30.33],"i":{"x":0.663,"y":0.977},"o":{"x":0.353,"y":0.538}},{"t":66.440518,"s":[30.3],"h":1},{"t":66.77391,"s":[30.3],"i":{"x":1,"y":1},"o":{"x":0,"y":0}},{"t":66.863925,"s":[30.31],"h":1},{"t":67.314,"s":[30.31],"i":{"x":1,"y":1},"o":{"x":0,"y":0}},{"t":70.134,"s":[30.3],"h":1},{"t":72,"s":[30.3],"i":{"x":0.531,"y":0.626},"o":{"x":0.227,"y":0.296}},{"t":72.036,"s":[29.69],"i":{"x":0.256,"y":0.535},"o":{"x":0.064,"y":0.184}},{"t":73.29,"s":[23.79],"i":{"x":0.66,"y":0.712},"o":{"x":0.315,"y":0.379}},{"t":74.574,"s":[20.63],"i":{"x":0.529,"y":0.583},"o":{"x":0.196,"y":0.223}},{"t":76.008,"s":[18],"i":{"x":0.543,"y":0.573},"o":{"x":0.207,"y":0.222}},{"t":77.04,"s":[16.44],"i":{"x":0.674,"y":0.676},"o":{"x":0.33,"y":0.332}},{"t":77.148,"s":[16.29],"i":{"x":0.711,"y":0.772},"o":{"x":0.34,"y":0.437}},{"t":82.08,"s":[10.94],"i":{"x":0.694,"y":0.697},"o":{"x":0.35,"y":0.353}},{"t":82.296,"s":[10.76],"i":{"x":0.555,"y":0.61},"o":{"x":0.21,"y":0.24}},{"t":85.77,"s":[8.2],"i":{"x":0.802,"y":0.845},"o":{"x":0.415,"y":0.523}},{"t":92.592,"s":[4.7],"i":{"x":0.712,"y":0.715},"o":{"x":0.365,"y":0.37}},{"t":93.006,"s":[4.54],"i":{"x":0.635,"y":0.672},"o":{"x":0.287,"y":0.321}},{"t":96.708,"s":[3.25],"i":{"x":0.566,"y":0.666},"o":{"x":0.221,"y":0.274}},{"t":103.932,"s":[1.44],"i":{"x":0.666,"y":0.673},"o":{"x":0.337,"y":0.345}},{"t":104.418,"s":[1.35],"i":{"x":0.513,"y":0.589},"o":{"x":0.141,"y":0.165}},{"t":108.252,"s":[0.74],"i":{"x":0.559,"y":0.801},"o":{"x":0.234,"y":0.377}},{"t":116.244,"s":[0.07],"i":{"x":0.755,"y":0.945},"o":{"x":0.414,"y":0.752}},{"t":119.586,"s":[0],"h":1},{"t":152.4,"s":[0],"h":1}]}},{"ty":7,"nm":"","v":{"a":0,"k":1}},{"ty":7,"nm":"","v":{"a":0,"k":0}}]}],"ip":0,"op":153.4,"st":0,"shapes":[{"ty":"gr","it":[{"ty":"rc","p":{"a":0,"k":[138.5,81.5]},"r":{"a":0,"k":0},"s":{"a":0,"k":[317,203]}},{"ty":"fl","c":{"a":0,"k":[0,0,0,0]},"o":{"a":0,"k":0}},{"ty":"tr","o":{"a":0,"k":100}}]},{"ty":"gr","it":[{"ty":"el","p":{"a":0,"k":[138.5,81.5]},"s":{"a":0,"k":[277,163]}},{"ty":"fl","c":{"a":0,"k":[0,0,0]},"o":{"a":0,"k":100}},{"ty":"tr","o":{"a":0,"k":100}}]}]},{"ind":6,"ty":3,"ks":{"p":{"a":0,"k":[20,20]}},"ip":0,"op":153.4,"st":0}]},{"id":"14","layers":[{"ind":13,"ty":4,"ks":{},"ip":0,"op":153.4,"st":0,"shapes":[{"ty":"rc","p":{"a":0,"k":[102,124.5]},"r":{"a":0,"k":0},"s":{"a":0,"k":[204,249]}},{"ty":"fl","c":{"a":0,"k":[0,0,0,0]},"o":{"a":0,"k":0}}]},{"ind":0,"ty":4,"ks":{"s":{"a":0,"k":[133.33,133.33]}},"ip":0,"op":153.4,"st":0,"shapes":[{"ty":"gr","it":[{"ty":"gr","it":[{"ty":"sh","ks":{"a":0,"k":{"c":false,"i":[[0,0],[-31.31,48.07],[28.29,18.43],[31.31,-48.07],[-28.29,-18.43]],"o":[[28.29,18.43],[31.31,-48.07],[-28.29,-18.43],[-31.31,48.07],[0,0]],"v":[[19.71,180.28],[127.62,126.6],[133.1,6.2],[25.19,59.88],[19.71,180.28]]}}},{"ty":"fl","c":{"a":0,"k":[0,0,0,1]},"o":{"a":0,"k":100}},{"ty":"tr","o":{"a":0,"k":100}}]},{"ty":"tr","o":{"a":0,"k":100}}]}]}]},{"id":"18","layers":[{"ind":16,"ty":0,"ks":{"p":{"a":0,"k":[20,20]}},"w":204,"h":249,"ip":0,"op":153.4,"st":0,"refId":"14"},{"ind":17,"ty":4,"ks":{},"ip":0,"op":153.4,"st":0,"shapes":[{"ty":"rc","p":{"a":0,"k":[122,144.5]},"r":{"a":0,"k":0},"s":{"a":0,"k":[244,289]}},{"ty":"fl","c":{"a":0,"k":[0,0,0,0]},"o":{"a":0,"k":0}}]}]},{"id":"21","layers":[{"ind":20,"ty":0,"parent":12,"ks":{"p":{"a":0,"k":[-20,-20]}},"ef":[{"ty":29,"ef":[{"ty":0,"nm":"","v":{"a":1,"k":[{"t":0,"s":[33.33],"h":1},{"t":11.585949,"s":[33.33],"i":{"x":0.599,"y":0.035},"o":{"x":0.134,"y":0.003}},{"t":19.556975,"s":[33.22],"i":{"x":0.736,"y":0.415},"o":{"x":0.428,"y":0.145}},{"t":27.528,"s":[32.43],"i":{"x":0.684,"y":0.681},"o":{"x":0.353,"y":0.349}},{"t":27.93,"s":[32.34],"i":{"x":0.659,"y":0.765},"o":{"x":0.343,"y":0.382}},{"t":32.847,"s":[31.33],"i":{"x":0.691,"y":0.807},"o":{"x":0.38,"y":0.558}},{"t":35.3055,"s":[31.1],"i":{"x":0.666,"y":0.616},"o":{"x":0.346,"y":0.353}},{"t":36.53475,"s":[31.03],"i":{"x":0.83,"y":0.884},"o":{"x":0.589,"y":0.433}},{"t":37.764,"s":[30.91],"i":{"x":0.701,"y":0.763},"o":{"x":0.397,"y":0.528}},{"t":41.034,"s":[30.76],"i":{"x":0.757,"y":0.834},"o":{"x":0.578,"y":0.523}},{"t":44.304,"s":[30.63],"i":{"x":0.645,"y":0.672},"o":{"x":0.322,"y":0.406}},{"t":46.152,"s":[30.57],"i":{"x":0.775,"y":0.844},"o":{"x":0.459,"y":0.438}},{"t":48,"s":[30.52],"i":{"x":0.748,"y":0.593},"o":{"x":0.369,"y":0.153}},{"t":50.409,"s":[30.35],"i":{"x":0.657,"y":0.514},"o":{"x":0.347,"y":0.214}},{"t":52.818,"s":[29.9],"i":{"x":0.772,"y":0.52},"o":{"x":0.48,"y":0.196}},{"t":58.668,"s":[25.92],"i":{"x":0.618,"y":0.599},"o":{"x":0.278,"y":0.265}},{"t":58.974,"s":[25.46],"i":{"x":0.569,"y":0.682},"o":{"x":0.391,"y":0.254}},{"t":64.518,"s":[11.9],"i":{"x":0.892,"y":0.939},"o":{"x":0.354,"y":0.649}},{"t":72,"s":[4.52],"i":{"x":0.704,"y":0.709},"o":{"x":0.319,"y":0.325}},{"t":72.288,"s":[4.36],"i":{"x":0.721,"y":0.822},"o":{"x":0.351,"y":0.525}},{"t":80.226,"s":[1.5],"i":{"x":0.655,"y":0.658},"o":{"x":0.327,"y":0.33}},{"t":80.382,"s":[1.47],"i":{"x":0.594,"y":0.765},"o":{"x":0.266,"y":0.402}},{"t":88.11,"s":[0.32],"i":{"x":0.666,"y":0.676},"o":{"x":0.335,"y":0.345}},{"t":88.482,"s":[0.29],"i":{"x":0.637,"y":0.999},"o":{"x":0.304,"y":0.647}},{"t":96,"s":[0],"h":1},{"t":152.4,"s":[0],"h":1}]}},{"ty":7,"nm":"","v":{"a":0,"k":1}},{"ty":7,"nm":"","v":{"a":0,"k":0}}]}],"w":244,"h":289,"ip":0,"op":153.4,"st":0,"refId":"18"},{"ind":12,"ty":3,"ks":{"p":{"a":0,"k":[21,21]}},"ip":0,"op":153.4,"st":0}]},{"id":"27","layers":[{"ind":26,"ty":4,"ks":{},"ip":0,"op":153.4,"st":0,"shapes":[{"ty":"rc","p":{"a":0,"k":[102,124.5]},"r":{"a":0,"k":0},"s":{"a":0,"k":[204,249]}},{"ty":"fl","c":{"a":0,"k":[0,0,0,0]},"o":{"a":0,"k":0}}]},{"ind":0,"ty":4,"ks":{"s":{"a":0,"k":[133.33,133.33]}},"ip":0,"op":153.4,"st":0,"shapes":[{"ty":"gr","it":[{"ty":"gr","it":[{"ty":"sh","ks":{"a":0,"k":{"c":false,"i":[[0,0],[31.31,-48.07],[-28.29,-18.43],[-31.31,48.07],[28.29,18.43]],"o":[[-28.29,-18.43],[-31.31,48.07],[28.29,18.43],[31.31,-48.07],[0,0]],"v":[[133.1,6.2],[25.19,59.88],[19.71,180.28],[127.62,126.6],[133.1,6.2]]}}},{"ty":"fl","c":{"a":0,"k":[0,0,0,1]},"o":{"a":0,"k":100}},{"ty":"tr","o":{"a":0,"k":100}}]},{"ty":"tr","o":{"a":0,"k":100}}]}]}]},{"id":"31","layers":[{"ind":29,"ty":0,"ks":{"p":{"a":0,"k":[20,20]}},"w":204,"h":249,"ip":0,"op":153.4,"st":0,"refId":"27"},{"ind":30,"ty":4,"ks":{},"ip":0,"op":153.4,"st":0,"shapes":[{"ty":"rc","p":{"a":0,"k":[122,144.5]},"r":{"a":0,"k":0},"s":{"a":0,"k":[244,289]}},{"ty":"fl","c":{"a":0,"k":[0,0,0,0]},"o":{"a":0,"k":0}}]}]},{"id":"34","layers":[{"ind":33,"ty":0,"parent":25,"ks":{"p":{"a":0,"k":[-20,-20]}},"ef":[{"ty":29,"ef":[{"ty":0,"nm":"","v":{"a":1,"k":[{"t":0,"s":[33.33],"h":1},{"t":11.60988,"s":[33.33],"i":{"x":0.833,"y":0.598},"o":{"x":0.508,"y":0.013}},{"t":19.56594,"s":[33.22],"i":{"x":0.729,"y":0.4},"o":{"x":0.418,"y":0.141}},{"t":27.522,"s":[32.43],"i":{"x":0.687,"y":0.685},"o":{"x":0.357,"y":0.355}},{"t":27.93,"s":[32.34],"i":{"x":0.646,"y":0.794},"o":{"x":0.346,"y":0.417}},{"t":34.101,"s":[31.18],"i":{"x":0.683,"y":0.778},"o":{"x":0.368,"y":0.562}},{"t":37.1865,"s":[30.96],"i":{"x":0.515,"y":0.473},"o":{"x":0.425,"y":0.404}},{"t":38.72925,"s":[30.88],"i":{"x":0.706,"y":0.789},"o":{"x":0.296,"y":0.306}},{"t":40.272,"s":[30.79],"i":{"x":0.393,"y":0.369},"o":{"x":0.375,"y":0.372}},{"t":42.288,"s":[30.71],"i":{"x":0.71,"y":0.817},"o":{"x":0.338,"y":0.362}},{"t":44.304,"s":[30.63],"i":{"x":0.588,"y":0.987},"o":{"x":0.317,"y":0.247}},{"t":47.684256,"s":[30.46],"h":1},{"t":47.746982,"s":[30.46],"i":{"x":0.626,"y":0.955},"o":{"x":0.357,"y":0.025}},{"t":50.459899,"s":[30.52],"h":1},{"t":50.530466,"s":[30.52],"i":{"x":0.671,"y":0.671},"o":{"x":0.412,"y":0.03}},{"t":53.016,"s":[30.43],"i":{"x":0.627,"y":0.985},"o":{"x":0.337,"y":0.482}},{"t":54.624565,"s":[30.36],"h":1},{"t":54.675301,"s":[30.36],"i":{"x":0.703,"y":0.559},"o":{"x":0.382,"y":0.024}},{"t":55.984806,"s":[30.4],"i":{"x":0.613,"y":0.962},"o":{"x":0.335,"y":0.509}},{"t":57.29431,"s":[30.44],"h":1},{"t":57.35648,"s":[30.44],"i":{"x":0.481,"y":0.051},"o":{"x":0.15,"y":0.028}},{"t":58.032313,"s":[30.43],"i":{"x":0.686,"y":0.645},"o":{"x":0.346,"y":0.268}},{"t":58.708146,"s":[30.4],"i":{"x":0.655,"y":0.98},"o":{"x":0.377,"y":0.558}},{"t":60.059812,"s":[30.34],"h":1},{"t":60.162,"s":[30.34],"i":{"x":0.656,"y":0.954},"o":{"x":0.352,"y":0.598}},{"t":61.135387,"s":[30.33],"h":1},{"t":61.240522,"s":[30.33],"i":{"x":0.761,"y":0.642},"o":{"x":0.521,"y":0.146}},{"t":61.750996,"s":[30.34],"h":1},{"t":62.26147,"s":[30.34],"i":{"x":0.718,"y":0.785},"o":{"x":0.107,"y":0.124}},{"t":62.771944,"s":[30.35],"h":1},{"t":64.197158,"s":[30.35],"i":{"x":1,"y":1},"o":{"x":0.47,"y":0.374}},{"t":64.955986,"s":[30.33],"i":{"x":0.452,"y":0.552},"o":{"x":0.005,"y":0.006}},{"t":65.714813,"s":[30.31],"h":1},{"t":67.314,"s":[30.31],"i":{"x":1,"y":1},"o":{"x":0,"y":0}},{"t":72,"s":[30.3],"i":{"x":1,"y":1},"o":{"x":0,"y":0}},{"t":75.426,"s":[30.31],"h":1},{"t":76.254654,"s":[30.31],"i":{"x":0.523,"y":0.329},"o":{"x":0.333,"y":0.061}},{"t":78.528491,"s":[30.33],"i":{"x":0.402,"y":0.489},"o":{"x":0.24,"y":0.298}},{"t":80.802327,"s":[30.35],"i":{"x":0.663,"y":0.529},"o":{"x":0.501,"y":0.169}},{"t":85.35,"s":[30.47],"i":{"x":0.74,"y":0.611},"o":{"x":0.3,"y":0.118}},{"t":91.779,"s":[30.94],"i":{"x":0.702,"y":0.722},"o":{"x":0.434,"y":0.316}},{"t":98.208,"s":[31.9],"i":{"x":0.639,"y":0.749},"o":{"x":0.337,"y":0.506}},{"t":104.004,"s":[32.42],"i":{"x":1,"y":1},"o":{"x":0.214,"y":0.22}},{"t":106.902,"s":[32.59],"i":{"x":0.749,"y":0.796},"o":{"x":0.521,"y":0.572}},{"t":109.8,"s":[32.75],"i":{"x":0.9,"y":0.948},"o":{"x":0.068,"y":0.523}},{"t":113.808,"s":[18.67],"i":{"x":0.714,"y":0.757},"o":{"x":0.357,"y":0.424}},{"t":116.478,"s":[14.55],"i":{"x":0.657,"y":0.679},"o":{"x":0.324,"y":0.347}},{"t":117.822,"s":[12.91],"i":{"x":0.562,"y":0.65},"o":{"x":0.237,"y":0.297}},{"t":123.15,"s":[8.04],"i":{"x":0.626,"y":0.663},"o":{"x":0.296,"y":0.327}},{"t":125.844,"s":[6.26],"i":{"x":0.562,"y":0.739},"o":{"x":0.238,"y":0.361}},{"t":137.778,"s":[1.56],"i":{"x":0.717,"y":0.773},"o":{"x":0.374,"y":0.454}},{"t":141.888,"s":[0.76],"i":{"x":0.576,"y":0.999},"o":{"x":0.245,"y":0.524}},{"t":152.4,"s":[0],"h":1}]}},{"ty":7,"nm":"","v":{"a":0,"k":1}},{"ty":7,"nm":"","v":{"a":0,"k":0}}]}],"w":244,"h":289,"ip":0,"op":153.4,"st":0,"refId":"31"},{"ind":25,"ty":3,"ks":{"p":{"a":0,"k":[21,21]}},"ip":0,"op":153.4,"st":0}]},{"id":"40","layers":[{"ind":39,"ty":4,"parent":38,"ks":{},"ef":[{"ty":29,"ef":[{"ty":0,"nm":"","v":{"a":1,"k":[{"t":0,"s":[33.33],"i":{"x":1,"y":1},"o":{"x":0,"y":0}},{"t":1.086,"s":[33.31],"i":{"x":0.817,"y":0.44},"o":{"x":0.533,"y":0.049}},{"t":10.602,"s":[28.56],"i":{"x":0.667,"y":0.611},"o":{"x":0.333,"y":0.283}},{"t":11.562,"s":[26.84],"i":{"x":0.453,"y":0.665},"o":{"x":0.357,"y":0.288}},{"t":17.496,"s":[11.37],"i":{"x":0.542,"y":0.701},"o":{"x":0.229,"y":0.356}},{"t":23.424,"s":[5.29],"i":{"x":0.637,"y":0.728},"o":{"x":0.307,"y":0.404}},{"t":28.56,"s":[2.69],"i":{"x":0.621,"y":0.755},"o":{"x":0.296,"y":0.43}},{"t":35.286,"s":[0.93],"i":{"x":0.624,"y":0.664},"o":{"x":0.295,"y":0.329}},{"t":37.062,"s":[0.66],"i":{"x":0.537,"y":0.628},"o":{"x":0.177,"y":0.213}},{"t":40.14,"s":[0.32],"i":{"x":0.699,"y":0.731},"o":{"x":0.367,"y":0.405}},{"t":41.31,"s":[0.22],"i":{"x":0.54,"y":0.769},"o":{"x":0.222,"y":0.347}},{"t":45.558,"s":[0.03],"i":{"x":0.752,"y":0.932},"o":{"x":0.414,"y":0.727}},{"t":47.664,"s":[0],"h":1},{"t":152.4,"s":[0],"h":1}]}},{"ty":7,"nm":"","v":{"a":0,"k":1}},{"ty":7,"nm":"","v":{"a":0,"k":0}}]}],"ip":0,"op":153.4,"st":0,"shapes":[{"ty":"gr","it":[{"ty":"rc","p":{"a":0,"k":[138.5,81.5]},"r":{"a":0,"k":0},"s":{"a":0,"k":[317,203]}},{"ty":"fl","c":{"a":0,"k":[0,0,0,0]},"o":{"a":0,"k":0}},{"ty":"tr","o":{"a":0,"k":100}}]},{"ty":"gr","it":[{"ty":"el","p":{"a":0,"k":[138.5,81.5]},"s":{"a":0,"k":[277,163]}},{"ty":"fl","c":{"a":0,"k":[0,0,0]},"o":{"a":0,"k":100}},{"ty":"tr","o":{"a":0,"k":100}}]}]},{"ind":38,"ty":3,"ks":{"p":{"a":0,"k":[20,20]}},"ip":0,"op":153.4,"st":0}]},{"id":"46","layers":[{"ind":45,"ty":4,"parent":44,"ks":{},"ef":[{"ty":29,"ef":[{"ty":0,"nm":"","v":{"a":1,"k":[{"t":0,"s":[33.33],"h":1},{"t":11.60988,"s":[33.33],"i":{"x":0.833,"y":0.598},"o":{"x":0.508,"y":0.013}},{"t":19.56594,"s":[33.22],"i":{"x":0.729,"y":0.4},"o":{"x":0.418,"y":0.141}},{"t":27.522,"s":[32.43],"i":{"x":0.687,"y":0.685},"o":{"x":0.357,"y":0.355}},{"t":27.93,"s":[32.34],"i":{"x":0.646,"y":0.794},"o":{"x":0.346,"y":0.417}},{"t":34.101,"s":[31.18],"i":{"x":0.683,"y":0.778},"o":{"x":0.368,"y":0.562}},{"t":37.1865,"s":[30.96],"i":{"x":0.515,"y":0.473},"o":{"x":0.425,"y":0.404}},{"t":38.72925,"s":[30.88],"i":{"x":0.706,"y":0.789},"o":{"x":0.296,"y":0.306}},{"t":40.272,"s":[30.79],"i":{"x":0.393,"y":0.369},"o":{"x":0.375,"y":0.372}},{"t":42.288,"s":[30.71],"i":{"x":0.71,"y":0.817},"o":{"x":0.338,"y":0.362}},{"t":44.304,"s":[30.63],"i":{"x":0.588,"y":0.987},"o":{"x":0.317,"y":0.247}},{"t":47.684256,"s":[30.46],"h":1},{"t":47.746982,"s":[30.46],"i":{"x":0.626,"y":0.955},"o":{"x":0.357,"y":0.025}},{"t":50.459899,"s":[30.52],"h":1},{"t":50.530466,"s":[30.52],"i":{"x":0.671,"y":0.671},"o":{"x":0.412,"y":0.03}},{"t":53.016,"s":[30.43],"i":{"x":0.627,"y":0.985},"o":{"x":0.337,"y":0.482}},{"t":54.624565,"s":[30.36],"h":1},{"t":54.675301,"s":[30.36],"i":{"x":0.703,"y":0.559},"o":{"x":0.382,"y":0.024}},{"t":55.984806,"s":[30.4],"i":{"x":0.613,"y":0.962},"o":{"x":0.335,"y":0.509}},{"t":57.29431,"s":[30.44],"h":1},{"t":57.35648,"s":[30.44],"i":{"x":0.481,"y":0.051},"o":{"x":0.15,"y":0.028}},{"t":58.032313,"s":[30.43],"i":{"x":0.686,"y":0.645},"o":{"x":0.346,"y":0.268}},{"t":58.708146,"s":[30.4],"i":{"x":0.655,"y":0.98},"o":{"x":0.377,"y":0.558}},{"t":60.059812,"s":[30.34],"h":1},{"t":60.162,"s":[30.34],"i":{"x":0.656,"y":0.954},"o":{"x":0.352,"y":0.598}},{"t":61.135387,"s":[30.33],"h":1},{"t":61.240522,"s":[30.33],"i":{"x":0.761,"y":0.642},"o":{"x":0.521,"y":0.146}},{"t":61.750996,"s":[30.34],"h":1},{"t":62.26147,"s":[30.34],"i":{"x":0.718,"y":0.785},"o":{"x":0.107,"y":0.124}},{"t":62.771944,"s":[30.35],"h":1},{"t":64.197158,"s":[30.35],"i":{"x":1,"y":1},"o":{"x":0.47,"y":0.374}},{"t":64.955986,"s":[30.33],"i":{"x":0.452,"y":0.552},"o":{"x":0.005,"y":0.006}},{"t":65.714813,"s":[30.31],"h":1},{"t":67.314,"s":[30.31],"i":{"x":1,"y":1},"o":{"x":0,"y":0}},{"t":72,"s":[30.3],"i":{"x":1,"y":1},"o":{"x":0,"y":0}},{"t":75.426,"s":[30.31],"h":1},{"t":75.62051,"s":[30.31],"i":{"x":0.559,"y":0.352},"o":{"x":0.387,"y":0.068}},{"t":78.052883,"s":[30.34],"i":{"x":0.721,"y":0.822},"o":{"x":0.547,"y":0.809}},{"t":80.485255,"s":[30.36],"i":{"x":0.611,"y":0.199},"o":{"x":0.159,"y":0.093}},{"t":82.917628,"s":[30.39],"i":{"x":0.591,"y":0.564},"o":{"x":0.4,"y":0.285}},{"t":85.35,"s":[30.47],"i":{"x":0.657,"y":0.543},"o":{"x":0.21,"y":0.151}},{"t":88.2,"s":[30.6],"i":{"x":0.214,"y":0.447},"o":{"x":0.049,"y":0.084}},{"t":88.29,"s":[29.4],"i":{"x":0.261,"y":0.594},"o":{"x":0.057,"y":0.197}},{"t":92.652,"s":[17.7],"i":{"x":0.476,"y":0.577},"o":{"x":0.161,"y":0.207}},{"t":97.2,"s":[12.45],"i":{"x":0.696,"y":0.775},"o":{"x":0.338,"y":0.452}},{"t":106.206,"s":[6.19],"i":{"x":0.649,"y":0.654},"o":{"x":0.319,"y":0.324}},{"t":106.668,"s":[5.95],"i":{"x":0.596,"y":0.765},"o":{"x":0.268,"y":0.409}},{"t":120.678,"s":[1.36],"i":{"x":0.66,"y":0.667},"o":{"x":0.329,"y":0.337}},{"t":121.2,"s":[1.26],"i":{"x":0.626,"y":0.999},"o":{"x":0.297,"y":0.643}},{"t":136.2,"s":[0],"h":1},{"t":152.4,"s":[0],"h":1}]}},{"ty":7,"nm":"","v":{"a":0,"k":1}},{"ty":7,"nm":"","v":{"a":0,"k":0}}]}],"ip":0,"op":153.4,"st":0,"shapes":[{"ty":"gr","it":[{"ty":"rc","p":{"a":0,"k":[138.5,81.5]},"r":{"a":0,"k":0},"s":{"a":0,"k":[317,203]}},{"ty":"fl","c":{"a":0,"k":[0,0,0,0]},"o":{"a":0,"k":0}},{"ty":"tr","o":{"a":0,"k":100}}]},{"ty":"gr","it":[{"ty":"el","p":{"a":0,"k":[138.5,81.5]},"s":{"a":0,"k":[277,163]}},{"ty":"fl","c":{"a":0,"k":[0,0,0]},"o":{"a":0,"k":100}},{"ty":"tr","o":{"a":0,"k":100}}]}]},{"ind":44,"ty":3,"ks":{"p":{"a":0,"k":[21,21]}},"ip":0,"op":153.4,"st":0}]},{"id":"52","layers":[{"ind":51,"ty":4,"parent":50,"ks":{},"ef":[{"ty":29,"ef":[{"ty":0,"nm":"","v":{"a":1,"k":[{"t":0,"s":[33.33],"h":1},{"t":11.562,"s":[33.33],"i":{"x":0.811,"y":0.414},"o":{"x":0.525,"y":0.001}},{"t":24,"s":[32.96],"i":{"x":0.758,"y":0.614},"o":{"x":0.441,"y":0.222}},{"t":26.652,"s":[32.45],"i":{"x":0.768,"y":0.639},"o":{"x":0.349,"y":0.187}},{"t":32.508,"s":[29.12],"i":{"x":0.712,"y":0.502},"o":{"x":0.433,"y":0.223}},{"t":36.978,"s":[21.47],"i":{"x":0.658,"y":0.673},"o":{"x":0.36,"y":0.346}},{"t":38.37,"s":[17.17],"i":{"x":0.44,"y":0.515},"o":{"x":0.097,"y":0.108}},{"t":39.528,"s":[14.13],"i":{"x":0.656,"y":0.737},"o":{"x":0.318,"y":0.414}},{"t":42.078,"s":[9.68],"i":{"x":0.46,"y":0.627},"o":{"x":0.156,"y":0.229}},{"t":47.178,"s":[5.04],"i":{"x":0.719,"y":0.763},"o":{"x":0.372,"y":0.442}},{"t":50.094,"s":[3.5],"i":{"x":0.848,"y":0.869},"o":{"x":0.375,"y":0.458}},{"t":53.733,"s":[2.17],"i":{"x":0.663,"y":0.742},"o":{"x":0.386,"y":0.48}},{"t":57.372,"s":[1.25],"i":{"x":1,"y":1},"o":{"x":0.302,"y":0.349}},{"t":60.375,"s":[0.74],"i":{"x":0.619,"y":0.719},"o":{"x":0.38,"y":0.492}},{"t":63.378,"s":[0.37],"i":{"x":0.789,"y":0.82},"o":{"x":0.317,"y":0.38}},{"t":66.09,"s":[0.17],"i":{"x":0.646,"y":0.777},"o":{"x":0.361,"y":0.508}},{"t":68.802,"s":[0.05],"i":{"x":0.742,"y":0.922},"o":{"x":0.404,"y":0.824}},{"t":72,"s":[0],"h":1},{"t":152.4,"s":[0],"h":1}]}},{"ty":7,"nm":"","v":{"a":0,"k":1}},{"ty":7,"nm":"","v":{"a":0,"k":0}}]}],"ip":0,"op":153.4,"st":0,"shapes":[{"ty":"gr","it":[{"ty":"rc","p":{"a":0,"k":[138.5,81.5]},"r":{"a":0,"k":0},"s":{"a":0,"k":[317,203]}},{"ty":"fl","c":{"a":0,"k":[0,0,0,0]},"o":{"a":0,"k":0}},{"ty":"tr","o":{"a":0,"k":100}}]},{"ty":"gr","it":[{"ty":"el","p":{"a":0,"k":[138.5,81.5]},"s":{"a":0,"k":[277,163]}},{"ty":"fl","c":{"a":0,"k":[0,0,0]},"o":{"a":0,"k":100}},{"ty":"tr","o":{"a":0,"k":100}}]}]},{"ind":50,"ty":3,"ks":{"p":{"a":0,"k":[21,21]}},"ip":0,"op":153.4,"st":0}]}],"fr":60,"h":1024,"ip":0,"layers":[{"ind":4,"ty":4,"parent":3,"ks":{},"ip":0,"op":153.4,"st":0,"shapes":[{"ty":"el","p":{"a":0,"k":[138.5,138.5]},"s":{"a":0,"k":[277,277]}},{"ty":"fl","c":{"a":0,"k":[0,0,0]},"o":{"a":0,"k":100}}]},{"ind":3,"ty":3,"parent":2,"ks":{"p":{"a":0,"k":[299,270]}},"ip":0,"op":153.4,"st":0},{"ind":10,"ty":0,"parent":5,"ks":{"a":{"a":0,"k":[20,20]},"o":{"a":1,"k":[{"t":0,"s":[0],"h":1},{"t":72,"s":[0],"i":{"x":0,"y":1},"o":{"x":0,"y":0}},{"t":120,"s":[100],"h":1},{"t":152.4,"s":[100],"h":1}]}},"w":317,"h":203,"ip":0,"op":153.4,"st":0,"refId":"8"},{"ind":5,"ty":3,"parent":2,"ks":{"a":{"a":0,"k":[138.5,81.5]},"p":{"a":0,"k":[143.883,569.534]},"r":{"a":0,"k":-123.08}},"ip":0,"op":153.4,"st":0},{"ind":23,"ty":0,"parent":11,"ks":{"a":{"a":0,"k":[21,21]},"o":{"a":1,"k":[{"t":0,"s":[0],"h":1},{"t":48,"s":[0],"i":{"x":0,"y":1},"o":{"x":0.5,"y":0}},{"t":96,"s":[100],"h":1},{"t":152.4,"s":[100],"h":1}]}},"w":245,"h":290,"ip":0,"op":153.4,"st":0,"refId":"21"},{"ind":11,"ty":3,"parent":2,"ks":{"p":{"a":0,"k":[42,140]}},"ip":0,"op":153.4,"st":0},{"ind":36,"ty":0,"parent":24,"ks":{"a":{"a":0,"k":[21,21]},"o":{"a":1,"k":[{"t":0,"s":[0],"h":1},{"t":109.8,"s":[0],"i":{"x":0,"y":1},"o":{"x":0,"y":0}},{"t":152.4,"s":[100],"h":1}]}},"w":245,"h":290,"ip":0,"op":153.4,"st":0,"refId":"34"},{"ind":24,"ty":3,"parent":2,"ks":{"p":{"a":0,"k":[627,445]}},"ip":0,"op":153.4,"st":0},{"ind":42,"ty":0,"parent":37,"ks":{"a":{"a":0,"k":[20,20]},"o":{"a":1,"k":[{"t":0,"s":[0],"i":{"x":0,"y":1},"o":{"x":0.5,"y":0}},{"t":48,"s":[100],"h":1},{"t":152.4,"s":[100],"h":1}]}},"w":317,"h":203,"ip":0,"op":153.4,"st":0,"refId":"40"},{"ind":37,"ty":3,"parent":2,"ks":{"a":{"a":0,"k":[138.5,81.5]},"p":{"a":0,"k":[728.882,264.534]},"r":{"a":0,"k":56.92}},"ip":0,"op":153.4,"st":0},{"ind":48,"ty":0,"parent":43,"ks":{"a":{"a":0,"k":[21,21]},"o":{"a":1,"k":[{"t":0,"s":[0],"h":1},{"t":88.2,"s":[0],"i":{"x":0,"y":1},"o":{"x":0,"y":0}},{"t":136.2,"s":[100],"h":1},{"t":152.4,"s":[100],"h":1}]}},"w":318,"h":204,"ip":0,"op":153.4,"st":0,"refId":"46"},{"ind":43,"ty":3,"parent":2,"ks":{"p":{"a":0,"k":[298,649]}},"ip":0,"op":153.4,"st":0},{"ind":54,"ty":0,"parent":49,"ks":{"a":{"a":0,"k":[21,21]},"o":{"a":1,"k":[{"t":0,"s":[0],"h":1},{"t":24,"s":[0],"i":{"x":0,"y":1},"o":{"x":0.5,"y":0}},{"t":72,"s":[100],"h":1},{"t":152.4,"s":[100],"h":1}]}},"w":318,"h":204,"ip":0,"op":153.4,"st":0,"refId":"52"},{"ind":49,"ty":3,"parent":2,"ks":{"p":{"a":0,"k":[298,0]}},"ip":0,"op":153.4,"st":0},{"ind":2,"ty":3,"parent":1,"ks":{"a":{"a":0,"k":[436.383,406]},"p":{"a":0,"k":[511.383,509]},"r":{"a":1,"k":[{"t":0,"s":[0],"i":{"x":0.255,"y":0.659},"o":{"x":0.492,"y":0}},{"t":152.4,"s":[900.51],"h":1}]},"s":{"a":1,"k":[{"t":0,"s":[100,100],"i":{"x":[1,1],"y":[1,1]},"o":{"x":[0,0],"y":[0,0]}},{"t":11.562,"s":[100,100],"i":{"x":[0,0],"y":[1,1]},"o":{"x":[0.5,0.5],"y":[0,0]}},{"t":72,"s":[110,110],"i":{"x":[0,0],"y":[1,1]},"o":{"x":[0.5,0.5],"y":[0,0]}},{"t":152.4,"s":[100,100],"h":1}]}},"ip":0,"op":153.4,"st":0},{"ind":1,"ty":3,"parent":0,"ks":{},"ip":0,"op":153.4,"st":0},{"ind":0,"ty":3,"ks":{},"ip":0,"op":153.4,"st":0}],"meta":{"g":"https://jitter.video"},"op":152.4,"v":"5.7.4","w":1024}